cactice/__init__.py
cactice/distance.py
cactice/fileio.py
cactice/grids.py
cactice/knn.py
cactice/mrf.py
cactice/plot.py
cactice/rns.py
cactice/tiles.py
cactice/utils.py
cactice/tests/__init__.py
cactice/tests/test_distance.py
cactice/tests/test_fileio.py
cactice/tests/test_grids.py
cactice/tests/test_knn.py
cactice/tests/test_metrics.py
cactice/tests/test_mrf.py
cactice/tests/test_rns.py
cactice/tests/test_tiles.py
cactice-0.0.7.dist-info/METADATA
cactice-0.0.7.dist-info/WHEEL
cactice-0.0.7.dist-info/top_level.txt
cactice-0.0.7.dist-info/RECORD
