Metadata-Version: 2.1
Name: cactice
Version: 0.0.7
Summary: computing agricultural crop lattices
Home-page: https://github.com/Computational-Plant-Science/cactice
Author: Computational Plant Science Lab
Author-email: wbonelli@uga.edu
License: BSD-3-Clause
Platform: UNKNOWN
Requires-Python: >=3.6.8
Requires-Dist: numpy
Requires-Dist: scipy
Requires-Dist: pandas
Requires-Dist: pytest
Requires-Dist: matplotlib
Requires-Dist: seaborn
Requires-Dist: jupyter
Requires-Dist: tqdm
Requires-Dist: click
